Workbook

Sheet Read me
A1: Family Split Master — input for the statement automation
A3: Upload this one workbook in the app's “Family split workbook” box (Investcorp or EFG).
A4: The engine reads each sheet by its header row, so keep the header rows exactly as they are.
A6: Members
A7: One row per investor per split investment — all investments in the same sheet.
A8: For a distribution the engine takes only the rows whose Analysis Code is that investment's.
A9: Investment (USD) = the investor's original investment in that deal.
A10: Share = dividend × investor's investment ÷ the deal's Investment Amount on the letter (Exhibit A).
A11: To add an investment: add its rows with its Analysis Code. To change one: edit its rows.
A12: Prefilled: 2019 US Industrial & Logistics, 27 investors, from the July 2026 split sheet.
A14: Holdings split
A15: Malco / Capital M fraction per holding — same layout as sheet “1” of Split_revised.xlsx.
... A23: Colours: yellow cells are inputs; blue text = values you typed; black = formulas.

Sheet Members
A1: Analysis Code | B1: Portfolio | C1: CM Code | D1: Investor | E1: Investment (USD)
A2: M00131794562 | B2: 2019 US Industrial & Logistics Portfolio | C2: CM0001 | D2: Malco Capital Investments LLC | E2: 7998.0116
A3: M00131794562 | B3: 2019 US Industrial & Logistics Portfolio | C3: CM0004 | D3: Moosa Abullatif Mustafa | E3: 0
A4: M00131794562 | B4: 2019 US Industrial & Logistics Portfolio | C4: CM0005 | D4: ASIA ARIF | E4: 5859.2677
A5: M00131794562 | B5: 2019 US Industrial & Logistics Portfolio | C5: CM0006 | D5: HAMDAN MOSTAFA | E5: 5859.2677
A6: M00131794562 | B6: 2019 US Industrial & Logistics Portfolio | C6: CM0007 | D6: REDHWANA ABBAS | E6: 5859.2677
A7: M00131794562 | B7: 2019 US Industrial & Logistics Portfolio | C7: CM0008 | D7: Heirs of Ali Abdullatif | E7: 9374.8172
A8: M00131794562 | B8: 2019 US Industrial & Logistics Portfolio | C8: CM0009 | D8: AL MANHAJ | E8: 43358.731
A9: M00131794562 | B9: 2019 US Industrial & Logistics Portfolio | C9: CM0011 | D9: FAIZA MOSTAFA | E9: 5859.2677
A10: M00131794562 | B10: 2019 US Industrial & Logistics Portfolio | C10: CM0012 | D10: RAANA ABBAS | E10: 5859.2677
A11: M00131794562 | B11: 2019 US Industrial & Logistics Portfolio | C11: CM0013 | D11: NARGEES | E11: 585.91567
A12: M00131794562 | B12: 2019 US Industrial & Logistics Portfolio | C12: CM0015 | D12: MUSTAFA ANWAR MUSTAFA | E12: 2214.7851
A13: M00131794562 | B13: 2019 US Industrial & Logistics Portfolio | C13: CM0016 | D13: ZAINAB AL AWADHI | E13: 1523.414
... A28: M00131794562 | B28: 2019 US Industrial & Logistics Portfolio | C28: CM0032 | D28: NILOOFER MOSTAFA | E28: 1186.8606

Sheet Holdings split
A1: No. | B1: Details | C1: Analysis Code | D1: Mapping | E1: Portfolio | F1: Malco | G1: capital M | H1: Check
A2: 1 | B2: Eastern Living Properties Portfolio | C2: Investcorp2 | D2: FVOCI | E2: Investcorp | F2: 1 | G2: 0 | H2: =IF(ABS(F2+G2-1)<0.001,"OK","Malco + capital M ≠ 1") -> OK
A3: 2 | B3: US Student Housing V Portfolio | C3: Investcorp4 | D3: FVOCI | E3: Investcorp | F3: 1 | G3: 0 | H3: =IF(ABS(F3+G3-1)<0.001,"OK","Malco + capital M ≠ 1") -> OK
A4: 3 | B4: Baltimore and Minneapolis Industrial Portfolio | C4: INVESTCORP5 | D4: FVOCI | E4: Investcorp | F4: 1 | G4: 0 | H4: =IF(ABS(F4+G4-1)<0.001,"OK","Malco + capital M ≠ 1") -> OK
A5: 4 | B5: US Student Housing IV Portfolio | C5: INVESTCORP11 | D5: FVOCI | E5: Investcorp | F5: 1 | G5: 0 | H5: =IF(ABS(F5+G5-1)<0.001,"OK","Malco + capital M ≠ 1") -> OK
A6: 5 | B6: US Industrial Growth Portfolio | C6: INVESTCORP6 | D6: FVOCI | E6: Investcorp | F6: 1 | G6: 0 | H6: =IF(ABS(F6+G6-1)<0.001,"OK","Malco + capital M ≠ 1") -> OK
A7: 6 | B7: US Student Housing II Portfolio | C7: Investcorp3 | D7: FVOCI | E7: Investcorp | F7: 1 | G7: 0 | H7: =IF(ABS(F7+G7-1)<0.001,"OK","Malco + capital M ≠ 1") -> OK
A8: 7 | B8: US Light Industrial Portfolio | C8: INVESTCORP7 | D8: FVOCI | E8: Investcorp | F8: 1 | G8: 0 | H8: =IF(ABS(F8+G8-1)<0.001,"OK","Malco + capital M ≠ 1") -> OK
A9: 8 | B9: US Student Housing Portfolio | C9: M00184632243 | D9: FVOCI | E9: Investcorp | F9: 1 | G9: 0 | H9: =IF(ABS(F9+G9-1)<0.001,"OK","Malco + capital M ≠ 1") -> OK
A10: 9 | B10: India Warehouse Portfolio | C10: Investcorp | D10: FVOCI | E10: Investcorp | F10: 1 | G10: 0 | H10: =IF(ABS(F10+G10-1)<0.001,"OK","Malco + capital M ≠ 1") -> OK
A11: 10 | B11: Las Vegas Infill Industrial Portfolio | C11: M00180124186 | D11: FVOCI | E11: Investcorp | F11: 1 | G11: 0 | H11: =IF(ABS(F11+G11-1)<0.001,"OK","Malco + capital M ≠ 1") -> OK
A12: 11 | B12: Boston and Minneapolis Properties Portfolio | C12: M00170835188 | D12: FVOCI | E12: Investcorp | F12: 1 | G12: 0 | H12: =IF(ABS(F12+G12-1)<0.001,"OK","Malco + capital M ≠ 1") -> OK
A13: 12 | B13: 2022 Residential Properties Portfolio | C13: M00168424083 | D13: FVOCI | E13: Investcorp | F13: 1 | G13: 0 | H13: =IF(ABS(F13+G13-1)<0.001,"OK","Malco + capital M ≠ 1") -> OK
... A46: 45 | B46: Nuqi Blox | C46: NUQI002 | D46: FVOCI | E46: Nuqi | F46: 1 | G46: 0 | H46: =IF(ABS(F46+G46-1)<0.001,"OK","Malco + capital M ≠ 1") -> OK

Sheet Summary
A1: Analysis Code | B1: Holding | C1: Capital M share | D1: Investors listed | E1: Their investment (USD) | F1: Status
A2: ='Holdings split'!C19 -> M00131794562 | B2: ='Holdings split'!B19 -> 2019 US Industrial & Logistics Portfolio | C2: ='Holdings split'!G19 -> 0.39 | D2: =COUNTIF(Members!$A:$A,A2) -> 27 | E2: =SUMIF(Members!$A:$A,A2,Members!$E:$E) -> 150000 | F2: =IF(D2=0,"No investors listed — entries will be withheld","Investors listed") -> Investors listed
A3: ='Holdings split'!C25 -> M00146223493 | B3: ='Holdings split'!B25 -> Saudi Hospitality | C3: ='Holdings split'!G25 -> 0.95833333 | D3: =COUNTIF(Members!$A:$A,A3) -> 0 | E3: =SUMIF(Members!$A:$A,A3,Members!$E:$E) -> 0 | F3: =IF(D3=0,"No investors listed — entries will be withheld","Investors listed") -> No investors listed — entries will be withheld
A4: ='Holdings split'!C26 -> M00229099272 | B4: ='Holdings split'!B26 -> Vectara | C4: ='Holdings split'!G26 -> 0.29999972 | D4: =COUNTIF(Members!$A:$A,A4) -> 0 | E4: =SUMIF(Members!$A:$A,A4,Members!$E:$E) -> 0 | F4: =IF(D4=0,"No investors listed — entries will be withheld","Investors listed") -> No investors listed — entries will be withheld
A5: ='Holdings split'!C27 -> M00155701502 | B5: ='Holdings split'!B27 -> 1QBit | C5: ='Holdings split'!G27 -> 0.69927536 | D5: =COUNTIF(Members!$A:$A,A5) -> 0 | E5: =SUMIF(Members!$A:$A,A5,Members!$E:$E) -> 0 | F5: =IF(D5=0,"No investors listed — entries will be withheld","Investors listed") -> No investors listed — entries will be withheld
A6: ='Holdings split'!C29 -> M00162315753 | B6: ='Holdings split'!B29 -> USA Rare Earth | C6: ='Holdings split'!G29 -> 0.71891289 | D6: =COUNTIF(Members!$A:$A,A6) -> 0 | E6: =SUMIF(Members!$A:$A,A6,Members!$E:$E) -> 0 | F6: =IF(D6=0,"No investors listed — entries will be withheld","Investors listed") -> No investors listed — entries will be withheld
A7: ='Holdings split'!C30 -> M00229099266 | B7: ='Holdings split'!B30 -> Elve | C7: ='Holdings split'!G30 -> 0.18152174 | D7: =COUNTIF(Members!$A:$A,A7) -> 0 | E7: =SUMIF(Members!$A:$A,A7,Members!$E:$E) -> 0 | F7: =IF(D7=0,"No investors listed — entries will be withheld","Investors listed") -> No investors listed — entries will be withheld
A8: ='Holdings split'!C31 -> ZZ0000000055 | B8: ='Holdings split'!B31 -> Analog Inference | C8: ='Holdings split'!G31 -> 0.29021739 | D8: =COUNTIF(Members!$A:$A,A8) -> 0 | E8: =SUMIF(Members!$A:$A,A8,Members!$E:$E) -> 0 | F8: =IF(D8=0,"No investors listed — entries will be withheld","Investors listed") -> No investors listed — entries will be withheld
A9: ='Holdings split'!C32 -> M00229099267 | B9: ='Holdings split'!B32 -> Cogntiv | C9: ='Holdings split'!G32 -> 0.30869565 | D9: =COUNTIF(Members!$A:$A,A9) -> 0 | E9: =SUMIF(Members!$A:$A,A9,Members!$E:$E) -> 0 | F9: =IF(D9=0,"No investors listed — entries will be withheld","Investors listed") -> No investors listed — entries will be withheld
A10: ='Holdings split'!C33 -> M00229099265 | B10: ='Holdings split'!B33 -> Paradromics | C10: ='Holdings split'!G33 -> 0.14347826 | D10: =COUNTIF(Members!$A:$A,A10) -> 0 | E10: =SUMIF(Members!$A:$A,A10,Members!$E:$E) -> 0 | F10: =IF(D10=0,"No investors listed — entries will be withheld","Investors listed") -> No investors listed — entries will be withheld
A11: ='Holdings split'!C34 -> M00146217830 | B11: ='Holdings split'!B34 -> Arsenal Bio | C11: ='Holdings split'!G34 -> 0.59834001 | D11: =COUNTIF(Members!$A:$A,A11) -> 0 | E11: =SUMIF(Members!$A:$A,A11,Members!$E:$E) -> 0 | F11: =IF(D11=0,"No investors listed — entries will be withheld","Investors listed") -> No investors listed — entries will be withheld
A12: ='Holdings split'!C35 -> ZZ0000000063 | B12: ='Holdings split'!B35 -> Good Chemistry | C12: ='Holdings split'!G35 -> 0.5 | D12: =COUNTIF(Members!$A:$A,A12) -> 0 | E12: =SUMIF(Members!$A:$A,A12,Members!$E:$E) -> 0 | F12: =IF(D12=0,"No investors listed — entries will be withheld","Investors listed") -> No investors listed — entries will be withheld
A13: ='Holdings split'!C38 -> KYG7387H1526 | B13: ='Holdings split'!B38 -> Vantage Data Centre | C13: ='Holdings split'!G38 -> 0.94668048 | D13: =COUNTIF(Members!$A:$A,A13) -> 0 | E13: =SUMIF(Members!$A:$A,A13,Members!$E:$E) -> 0 | F13: =IF(D13=0,"No investors listed — entries will be withheld","Investors listed") -> No investors listed — entries will be withheld
A14: ='Holdings split'!C39 -> XS3101460304 | B14: ='Holdings split'!B39 -> Dar Al Arkan Sukuk 7.250% 02/07/2030 | C14: ='Holdings split'!G39 -> 1 | D14: =COUNTIF(Members!$A:$A,A14) -> 0 | E14: =SUMIF(Members!$A:$A,A14,Members!$E:$E) -> 0 | F14: =IF(D14=0,"No investors listed — entries will be withheld","Investors listed") -> No investors listed — entries will be withheld
A15: ='Holdings split'!C40 -> M00229099270 | B15: ='Holdings split'!B40 -> US Living Debt Fund I | C15: ='Holdings split'!G40 -> 0.63707729 | D15: =COUNTIF(Members!$A:$A,A15) -> 0 | E15: =SUMIF(Members!$A:$A,A15,Members!$E:$E) -> 0 | F15: =IF(D15=0,"No investors listed — entries will be withheld","Investors listed") -> No investors listed — entries will be withheld
A16: ='Holdings split'!C41 -> M00229099271 | B16: ='Holdings split'!B41 -> Wadi Al Amal | C16: ='Holdings split'!G41 -> 0.48758056 | D16: =COUNTIF(Members!$A:$A,A16) -> 0 | E16: =SUMIF(Members!$A:$A,A16,Members!$E:$E) -> 0 | F16: =IF(D16=0,"No investors listed — entries will be withheld","Investors listed") -> No investors listed — entries will be withheld
A17: ='Holdings split'!C42 -> M00214974768 | B17: ='Holdings split'!B42 -> Flooss Holding | C17: ='Holdings split'!G42 -> 0.49932065 | D17: =COUNTIF(Members!$A:$A,A17) -> 0 | E17: =SUMIF(Members!$A:$A,A17,Members!$E:$E) -> 0 | F17: =IF(D17=0,"No investors listed — entries will be withheld","Investors listed") -> No investors listed — entries will be withheld
